README.md
README.rst
setup.py
vfxpaths/__init__.py
vfxpaths/error.py
vfxpaths/global_config.py
vfxpaths/initialization.py
vfxpaths/path.py
vfxpaths/resolve.py
vfxpaths/utils.py
vfxpaths/version.py
vfxpaths.egg-info/PKG-INFO
vfxpaths.egg-info/SOURCES.txt
vfxpaths.egg-info/dependency_links.txt
vfxpaths.egg-info/not-zip-safe
vfxpaths.egg-info/top_level.txt
vfxpaths/ability/__init__.py
vfxpaths/ability/path_env_resolve.py
vfxpaths/ability/path_operation.py
vfxpaths/ability/regex_match.py