Metadata-Version: 1.2
Name: vfxpaths
Version: 1.2.0
Summary: Common processing module of VFX path
Home-page: https://github.com/VFXToolkits/vfxpaths
Author: zuokangbo
Author-email: zuokangbo@outlook.com
License: MIT License
Keywords: vfx,vfxpath,vfxfile,paths,read,write
Platform: UNKNOWN
Requires-Python: >=3.7
